CiscoAutomationFramework/FirmwareBase.py
CiscoAutomationFramework/FirmwareDetect.py
CiscoAutomationFramework/IOS.py
CiscoAutomationFramework/IOSXE.py
CiscoAutomationFramework/NXOS.py
CiscoAutomationFramework/TransportEngines.py
CiscoAutomationFramework/__init__.py
CiscoAutomationFramework/Parsers/ConfigParser.py
CiscoAutomationFramework/Parsers/ConfigSectionTypes.py
CiscoAutomationFramework/Parsers/__init__.py
CiscoAutomationFramework-0.8.16.dist-info/LICENSE
CiscoAutomationFramework-0.8.16.dist-info/METADATA
CiscoAutomationFramework-0.8.16.dist-info/WHEEL
CiscoAutomationFramework-0.8.16.dist-info/top_level.txt
CiscoAutomationFramework-0.8.16.dist-info/RECORD
