Metadata-Version: 2.1
Name: CiscoAutomationFramework
Version: 0.8.16
Summary: Framework for issuing commands and retrieving consistent data on Cisco devices
Home-page: https://github.com/superadm1n/CiscoAutomationFramework
Author: Kyle Kowalczyk
Author-email: kowalkyl@gmail.com
License: Apache 2.0
Keywords: cisco automation framework network
Platform: UNKNOWN
Classifier: Development Status :: 4 - Beta
Classifier: Intended Audience :: System Administrators
Classifier: License :: OSI Approved :: Apache Software License
Classifier: Programming Language :: Python :: 3.9
License-File: LICENSE
Requires-Dist: paramiko
Requires-Dist: pyserial (==3.4)
